<?xml version="1.0" encoding="utf-8" ?>
<dwsync>
<file name="black.png" server="195.220.155.5//eg_test/" local="130268365840000000" remote="130380457800000000" />
<file name="dark-blue.png" server="195.220.155.5//eg_test/" local="130268365840000000" remote="130380457800000000" />
<file name="green.png" server="195.220.155.5//eg_test/" local="130268365840000000" remote="130380457800000000" />
<file name="light-blue.png" server="195.220.155.5//eg_test/" local="130268365840000000" remote="130380457800000000" />
<file name="lone_round_fractal.png" server="195.220.155.5//eg_test/" local="130373167927667701" remote="130380457800000000" />
<file name="lone_round_peanut.png" server="195.220.155.5//eg_test/" local="130376307559290290" remote="130380457800000000" />
<file name="peanut.png" server="195.220.155.5//eg_test/" local="130372771682969582" remote="130380457800000000" />
<file name="purple.png" server="195.220.155.5//eg_test/" local="130268365840000000" remote="130380457800000000" />
<file name="red.png" server="195.220.155.5//eg_test/" local="130268365840000000" remote="130380457800000000" />
<file name="social_round_fractal.png" server="195.220.155.5//eg_test/" local="130373170971201782" remote="130380457800000000" />
<file name="social_round_peanut.png" server="195.220.155.5//eg_test/" local="130376314786343653" remote="130380457800000000" />
<file name="sound.mp3" server="195.220.155.5//eg_test/" local="130280438220000000" remote="130380457800000000" />
<file name="welcome_fractal.png" server="195.220.155.5//eg_test/" local="130268365840000000" remote="130380457800000000" />
<file name="welcome_peanut.png" server="195.220.155.5//eg_test/" local="130376262549184517" remote="130380457800000000" />
<file name="yellow.png" server="195.220.155.5//eg_test/" local="130268365840000000" remote="130380156000000000" />
</dwsync>